docViewer/__init__.py
docViewer/__main__.py
docViewer/cache.py
docViewer/config.py
docViewer/logging.py
docViewer/plantuml.py
docViewer/pygments.py
docViewer/render.py
docViewer/openapi/__init__.py
docViewer/openapi/templates/swagger-editor.html
docViewer/openapi/templates/swagger-ui.html
docViewer/preview_server/__init__.py
docViewer/preview_server/config.py
docViewer/preview_server/urls.py
docViewer/preview_server/views.py
docViewer/preview_server/web.py
docViewer/preview_server/websocket.py
docViewer/preview_server/templates/base.html
docViewer/preview_server/templates/error.html
docViewer/preview_server/templates/lite-preview.html
docViewer/rst/__init__.py
docViewer/rst/default.css
docViewer/rst/directives.py
docViewer/rst/template.txt
docViewer/rst/template_body.txt
docViewer-1.1.0.data/scripts/preview-openapi
docViewer-1.1.0.data/scripts/previewDoc
docViewer-1.1.0.data/scripts/renderDoc
docViewer-1.1.0.dist-info/LICENSE
docViewer-1.1.0.dist-info/METADATA
docViewer-1.1.0.dist-info/WHEEL
docViewer-1.1.0.dist-info/top_level.txt
docViewer-1.1.0.dist-info/RECORD
