Metadata-Version: 2.1
Name: docViewer
Version: 1.1.0
Summary: document tool
Home-page: UNKNOWN
Author: Abraham
Author-email: abraham.liu@hotmail.com
License: UNKNOWN
Platform: UNKNOWN
Classifier: Programming Language :: Python :: 3
Classifier: Operating System :: OS Independent
Requires-Dist: click
Requires-Dist: p-config (>=1.2.0)
Requires-Dist: docutils
Requires-Dist: requests
Requires-Dist: tornado
